spotfirepill/__init__.py
spotfirepill/spotfirepill.py
spotfirepill-0.15.dist-info/LICENSE
spotfirepill-0.15.dist-info/METADATA
spotfirepill-0.15.dist-info/WHEEL
spotfirepill-0.15.dist-info/top_level.txt
spotfirepill-0.15.dist-info/RECORD
