Metadata-Version: 2.1
Name: spotfirepill
Version: 0.15
Summary: This will use spotfire REST API end points to login & execute the jobs
Home-page: https://github.com/tagnev/spotfirepill
Author: Vengat
Author-email: tagnev.vengat@gmail.com
License: UNKNOWN
Platform: UNKNOWN
Classifier: Programming Language :: Python :: 3
Classifier: License :: OSI Approved :: MIT License
Classifier: Operating System :: OS Independent
Requires-Python: >=3.6
Requires-Dist: requests
